parseid/__init__.py
parseid/build.py
parseid/constants.py
parseid/ditrie.py
parseid/parse.py
parseid/process.py
parseid/read_file.py
parseid/trie.py
parseid/trie_node.py
parseid-0.2.0.dist-info/METADATA
parseid-0.2.0.dist-info/WHEEL
parseid-0.2.0.dist-info/top_level.txt
parseid-0.2.0.dist-info/RECORD
