Metadata-Version: 2.1
Name: parseid
Version: 0.2.0
Summary: suck, parse identifiers or accession numbers
Home-page: https://github.com/Tiezhengyuan/parse_identifier
Author: Tiezheng Yuan
Author-email: tiezhengyuan@hotmail.com
Keywords: pypi,cicd,python
Classifier: Development Status :: 1 - Planning
Classifier: Intended Audience :: Developers
Classifier: Programming Language :: Python :: 3
Classifier: Operating System :: Unix
Classifier: Operating System :: MacOS :: MacOS X
Classifier: Operating System :: Microsoft :: Windows
Requires-Dist: bioomics
Requires-Dist: numpy
Requires-Dist: pandas
Requires-Dist: requests
Requires-Dist: obonet
Requires-Dist: python-dotenv
